Workbook

Sheet Read Me
B2: Tongda Express — Historical Financials, IPO to Date
B3: ZTO / YTO / STO / Yunda · FY2016–FY2025 · all figures RMB million unless stated
B5: All four listed in 2016 | C5: ZTO IPO'd on the NYSE in October 2016 (USD1.4bn, the largest US IPO of that year). YTO reverse-merged onto the Shanghai exchange, and STO and Yunda reverse-merged onto Shenzhen, all in 2016. FY2016 is therefore the common starting point.
B6: Colour convention | C6: BLUE = reported figure, verified against a filing or company release in this build. ORANGE = figure believed correct but NOT verified in this build — confirm before use. BLACK = formula. Blank = not yet sourced.
B7: Coverage — be aware | C7: ZTO is near-complete: it files with the SEC in English and its releases carry full P&L, cash flow and unit-cost detail. YTO, STO and Yunda are A-share filers reporting only in Chinese; this build has them solid for FY2022–FY2025 and patchy before that. The Coverage Map below shows exactly where the holes are.
B8: Critical comparability note | C8: ZTO records the franchisee last-mile delivery fee NET; YTO, STO and Yunda record it GROSS. So ZTO's unit revenue of ~RMB1.2 and the others' ~RMB2.0–2.2 are NOT comparable as reported. Add roughly RMB1.25 to both ZTO's unit revenue and unit cost to put it on the same basis. STO's disclosed unit pickup-and-delivery cost of RMB1.27 (2025) is the anchor for that adjustment.
B9: Unit cost definitions differ too | C9: ZTO's 'unit cost' in its own commentary excludes the delivery fee and strips out freight forwarding. The A-share names' 单票成本 is all-in. Compare the transport and sorting lines — those ARE directly comparable — rather than the totals.
B10: Capex | C10: Only sporadically disclosed by all four. ZTO gives it in earnings calls rather than releases. Cumulative 2016–2023 capex: ZTO RMB47.3bn, YTO RMB30.6bn (Huaxi Securities). Annual series needs the cash flow statements from each annual report.
B12: Coverage Map
B13: ZTO | C13: 2016 partial · 2017–2018 full (incl. cost lines) · 2019–2023 headline only · 2024–2025 full
B14: YTO | C14: 2016–2021 not sourced · 2022–2023 unit economics · 2024–2025 full
B15: STO | C15: 2016–2021 not sourced · 2022–2023 partial · 2024 headline · 2025 full incl. leg-level cost split
B16: Yunda | C16: 2016–2021 not sourced · 2022–2023 full incl. leg-level cost split · 2024–2025 headline
B18: To complete the series | C18: The A-share gaps are all fillable from CNINFO (www.cninfo.com.cn) — search the ticker, filter to 年度报告, and pull the 主要会计数据 and 分行业经营情况 tables. ZTO's gaps are in its annual 6-K exhibits on SEC EDGAR (CIK 1677250). Links on the Sources tab.
B19: Prepared | C19: 3 September 2026.

Sheet ZTO
B2: ZTO Express (NYSE: ZTO / SEHK: 2057) — FY2016–FY2025
B3: US GAAP, RMB. Source: annual 6-K exhibits, SEC EDGAR CIK 1677250.
B5: RMB million unless stated | C5: 2016 | D5: 2017 | E5: 2018 | F5: 2019 | G5: 2020 | H5: 2021 | I5: 2022 | J5: 2023 | K5: 2024 | L5: 2025 | M5: Note
B6: Volumes & share
B7: Parcel volume (mn) | C7: 4460 | D7: 6219 | E7: 8524 | F7: 12122 | G7: 17010 | H7: 22300 | I7: 24400 | J7: 30202 | K7: 34013 | L7: 38500 | M7: 2017/18 from FY18 release; 2021–25 from company releases
B8: Market share (%) | E8: 0.168 | F8: 0.191 | H8: 0.206 | I8: 0.221 | J8: 0.229 | M8: Share fell below 20% in 2024 for the first time since 2020
B9: Income statement
B10: Total revenues | C10: 9786 | D10: 13060 | E10: 17604 | F10: 22110 | G10: 25214 | H10: 30406 | I10: 35377 | J10: 38419 | K10: 44281 | L10: 49099
B11: o/w express delivery services | D11: 12174 | E11: 15400 | L11: 45726 | M11: Segment split only pulled for these years
B12: Total cost of revenues | D12: 8714 | E12: 12240 | K12: 30600 | L12: 36827
B13: Line-haul transportation cost | D13: 4798 | E13: 5758 | L13: 13971
B14: Sorting hub cost | D14: 2439 | E14: 3198 | L14: 9838
B15: Freight forwarding cost | D15: 260 | E15: 1239 | L15: 760
B16: Cost of accessories sold | D16: 367 | E16: 492 | L16: 578
B17: Other costs | D17: 851 | E17: 1553 | L17: 11681 | M17: 2025 +96% on key-account service costs
B18: Gross profit | D18: 4346 | E18: 5365 | H18: 6589 | I18: 9039 | K18: 13700 | L18: 12272
B19: SG&A | D19: 781 | E19: 1211 | L19: 2638
B20: Income from operations | D20: 3748 | E20: 4332 | L20: 10475
B21: Net income | D21: 3159 | E21: 4388 | H21: 4701 | I21: 6659 | J21: 8755 | K21: 8888 | L21: 9513 | M21: 2025 = net profit attributable
B22: Adjusted net income | D22: 3230 | E22: 4201 | F22: 5300 | H22: 4900 | I22: 6806 | J22: 9000 | K22: 10200 | L22: 9513
B23: Adjusted EBITDA | D23: 4452 | E23: 5858 | G23: 7155 | H23: 8301 | I23: 11289 | K23: 16400
B24: Margins
B25: Gross margin | D25: =D18/D10 -> 0.33277182 | E25: =E18/E10 -> 0.30476028 | H25: =H18/H10 -> 0.21670065 | I25: =I18/I10 -> 0.25550499 | K25: =K18/K10 -> 0.30938777 | L25: =L18/L10 -> 0.24994399 | M25: Formula = gross profit / total revenues
B26: Net margin | D26: =D21/D10 -> 0.24188361 | E26: =E21/E10 -> 0.24926153 | H26: =H21/H10 -> 0.15460764 | I26: =I21/I10 -> 0.18822964 | K26: =K21/K10 -> 0.20071814 | L26: =L21/L10 -> 0.1937514
B27: Unit economics (RMB per parcel)
B28: Unit revenue — total | C28: =IFERROR(C10/C7,"") -> 2.1941704 | D28: =IFERROR(D10/D7,"") -> 2.1000161 | E28: =IFERROR(E10/E7,"") -> 2.0652276 | F28: =IFERROR(F10/F7,"") -> 1.8239564 | G28: =IFERROR(G10/G7,"") -> 1.4823045 | H28: =IFERROR(H10/H7,"") -> 1.3634978 | I28: =IFERROR(I10/I7,"") -> 1.449877 | J28: =IFERROR(J10/J7,"") -> 1.2720681 | ... L28: =IFERROR(L10/L7,"") -> 1.2752987 | M28: Filled by formula below where both inputs exist
B29: Unit revenue — core express (reported) | I29: 1.34 | J29: 1.24 | M29: Company/press-reported core ASP. NETS OUT the delivery fee.
B30: Unit cost — reported basis | J30: 0.86 | L30: 0.94 | M30: Ex-delivery fee, ex-freight forwarding
B31: Unit line-haul cost | L31: 0.36 | M31: 2025 -RMB0.05 YoY
B32: Unit sorting cost | L32: 0.26 | M32: 2025 -RMB0.01 YoY
B33: Cash flow & capex
B34: Net cash from operating activities | D34: 3631 | E34: 4404 | F34: 6304 | G34: 4951 | H34: 7220 | I34: 11479 | J34: 13361 | K34: 11429
B35: Capital expenditure | K35: 5900 | M35: Cumulative 2016–23 capex RMB47.3bn (Huaxi). Annual series to be pulled from 20-F cash flow statements.
B37: ZTO's reported unit revenue and unit cost exclude the franchisee last-mile delivery fee, which is recorded net. To compare with YTO/STO/Yunda, add ~RMB1.25 to both.
B38: Gross margin fell from 33.3% (2017) to 25.0% (2025) — the clearest single measure of what a decade of price competition did to the best operator in the sector.

Sheet YTO
B2: YTO Express 圆通速递 (SSE: 600233) — FY2016–FY2025
B3: PRC GAAP, RMB. Source: annual reports on CNINFO. Reverse-merged onto the SSE in 2016.
B5: RMB million unless stated | C5: 2016 | D5: 2017 | E5: 2018 | F5: 2019 | G5: 2020 | H5: 2021 | I5: 2022 | J5: 2023 | K5: 2024 | L5: 2025 | M5: Note
B6: Volumes & share
B7: Parcel volume (mn) | I7: 17400 | J7: 21200 | K7: 26573 | L7: 31144 | M7: 2023 derived from 2024's +25.32%
B8: Market share (%) | K8: 0.1518
B9: Income statement
B10: Total revenues | K10: 60900 | L10: 75277 | M10: 2024 figure is express business revenue (+19.04%)
B11: o/w express segment revenue | L11: 69590 | M11: +11.72% YoY
B12: Net profit attributable | L12: 4322 | M12: +7.73%
B13: o/w express segment | L13: 4614 | M13: +7.14%; = RMB0.148 per parcel
B14: Margins
B15: Express segment gross margin | J15: 0.1027 | K15: 0.0919 | L15: 0.09 | M15: 2022: 11.12%
B16: Unit economics (RMB per parcel)
B17: Unit revenue — express product | I17: 2.59 | J17: 2.41 | L17: 2.19 | M17: 2024 declined ~5%; 2025 -4.61%
B18: Unit cost — total | J18: 2.18 | L18: 2 | M18: 2023 -5.99%. 2025 derived from ~9% segment gross margin; 1H25 disclosed at 2.02
B19: Unit transport cost | L19: 0.37 | M19: -10.35% YoY
B20: Unit hub operating cost | L20: 0.27 | M20: -3.75% YoY
B21: Cash flow & capex
B22: Capital expenditure | M22: Cumulative 2016–23 capex RMB30.6bn (Huaxi). Annual series from CNINFO cash flow statements.
B24: YTO records the franchisee delivery fee GROSS, so its ~RMB2.2 unit revenue is directly comparable with STO and Yunda, and with J&T China — but NOT with ZTO as reported.
B25: Its revenue mix includes freight forwarding and air/international, which run at different margins (2024: express 9.19%, freight forwarding 8.48%, international -9.69%). Use segment, not group, figures for unit economics.

Sheet STO
B2: STO Express 申通快递 (SZSE: 002468) — FY2016–FY2025
B3: PRC GAAP, RMB. Source: annual reports on CNINFO. Reverse-merged into Aidixi (002468) in 2016.
B5: RMB million unless stated | C5: 2016 | D5: 2017 | E5: 2018 | F5: 2019 | G5: 2020 | H5: 2021 | I5: 2022 | J5: 2023 | K5: 2024 | L5: 2025 | M5: Note
B6: Volumes & share
B7: Parcel volume (mn) | I7: 12900 | K7: 22700 | L7: 26139 | M7: 2022 +16.9% (fastest in sector that year); 2025 +15.0%
B8: Market share (%) | K8: 0.1298 | M8: Only name to gain share in 2024
B9: Income statement
B10: Total revenues | L10: 55586 | M10: +17.84% YoY
B11: Net profit attributable | K11: 1040 | M11: +205% YoY — fastest profit growth in the Tongda group
B12: Net profit ex-exceptionals | K12: 1017 | M12: +199.55%
B13: Unit economics (RMB per parcel)
B14: Unit revenue | I14: 2.52 | K14: 2.05 | L14: 2.1 | M14: 2025 uplift partly from Danniao consolidation in November
B15: Unit cost — total | J15: 2.15 | L15: 1.98 | M15: 2023 -10.9%; 2025 +RMB0.04
B16: Unit pickup + delivery cost | L16: 1.27 | M16: +RMB0.05. THE ANCHOR for normalising ZTO
B17: Unit sorting cost | L17: 0.31 | M17: -RMB0.02
B18: Unit transport cost | L18: 0.39 | M18: +RMB0.02
B19: Cash flow & capex
B20: Capital expenditure | M20: To be pulled from CNINFO cash flow statements
B22: STO has the best cost disclosure of the four — it publishes the full leg-level split (pickup+delivery / sorting / transport), which is what makes cross-company normalisation possible at all.
B23: Danniao (丹鸟), acquired from Cainiao and consolidated from November 2025, lifts unit revenue but brings direct-network last-mile cost. FY2025 and FY2026 unit costs will not be comparable.

Sheet Yunda
B2: Yunda Express 韵达股份 (SZSE: 002120) — FY2016–FY2025
B3: PRC GAAP, RMB. Source: annual reports on SZSE/CNINFO. Reverse-merged into Xinhai (002120) in 2016.
B5: RMB million unless stated | C5: 2016 | D5: 2017 | E5: 2018 | F5: 2019 | G5: 2020 | H5: 2021 | I5: 2022 | J5: 2023 | K5: 2024 | L5: 2025 | M5: Note
B6: Volumes & share
B7: Parcel volume (mn) | I7: 17600 | J7: 18854 | K7: 23800 | L7: 25601 | M7: 2022 -4.3%; 2024 +26.14%; 2025 +7.65%
B8: Market share (%) | J8: 0.1428 | K8: 0.1358 | L8: 0.1287 | M8: Three consecutive years of share loss
B9: Income statement
B10: Total revenues | J10: 44983 | L10: 51475 | M10: 2023 -5.17%; 2025 +6.04%
B11: o/w express service revenue | K11: 48800 | L11: 50764 | M11: 2024 +9.3%; 2025 +6.01%
B12: Net profit attributable | J12: 1625 | K12: 1914 | L12: 1171 | M12: 2025 -38.79% — the sharpest decline in the group
B13: Margins
B14: Gross margin | I14: 0.0839 | J14: 0.0852
B15: Unit economics (RMB per parcel)
B16: Unit revenue | I16: 2.55 | L16: 1.983 | M16: 2025 derived = express service revenue / volume. Quarterly path 1.98 / 1.91 / 1.95 / 2.14
B17: Unit cost — total | I17: 2.34 | J17: 2.1 | L17: 1.85 | M17: 2025 DERIVED, ±RMB0.05 — Yunda publishes no headline unit total cost
B18: Unit delivery fee | J18: 1.21 | M18: -RMB0.13 YoY
B19: Unit transport cost | J19: 0.5 | M19: -RMB0.11 YoY; 2025 core unit op cost -10.29%
B20: Unit sorting cost | J20: 0.37 | M20: broadly flat YoY
B21: Net profit per parcel | L21: =L12/L7 -> 0.045740401 | M21: Formula. ~RMB0.046 — roughly one fifth of ZTO's
B22: Cash flow & capex
B23: Capital expenditure | M23: To be pulled from CNINFO cash flow statements
B25: Yunda is the clearest case study in the sector: lowest unit cost of the four, and the weakest profitability. In 2025 it grew volume 7.65% and saw profit fall 38.8%.
B26: It discloses the delivery-fee line explicitly (RMB1.21 in 2023), which independently corroborates STO's RMB1.27 and J&T's USD0.18.

Sheet Unit Economics
B2: Cross-company unit economics
B3: RMB per parcel. Green = linked from company tabs. Read the normalisation warning before comparing ZTO with the rest.
B5: RMB per parcel | C5: 2016 | D5: 2017 | E5: 2018 | F5: 2019 | G5: 2020 | H5: 2021 | I5: 2022 | J5: 2023 | K5: 2024 | L5: 2025 | M5: Note
B6: Parcel volume (mn)
B7: ZTO | C7: =IFERROR(IF(ZTO!C7="","",ZTO!C7),"") -> 4460 | D7: =IFERROR(IF(ZTO!D7="","",ZTO!D7),"") -> 6219 | E7: =IFERROR(IF(ZTO!E7="","",ZTO!E7),"") -> 8524 | F7: =IFERROR(IF(ZTO!F7="","",ZTO!F7),"") -> 12122 | G7: =IFERROR(IF(ZTO!G7="","",ZTO!G7),"") -> 17010 | H7: =IFERROR(IF(ZTO!H7="","",ZTO!H7),"") -> 22300 | I7: =IFERROR(IF(ZTO!I7="","",ZTO!I7),"") -> 24400 | J7: =IFERROR(IF(ZTO!J7="","",ZTO!J7),"") -> 30202 | ... L7: =IFERROR(IF(ZTO!L7="","",ZTO!L7),"") -> 38500
B8: YTO | C8: =IFERROR(IF(YTO!C7="","",YTO!C7),"") | D8: =IFERROR(IF(YTO!D7="","",YTO!D7),"") | E8: =IFERROR(IF(YTO!E7="","",YTO!E7),"") | F8: =IFERROR(IF(YTO!F7="","",YTO!F7),"") | G8: =IFERROR(IF(YTO!G7="","",YTO!G7),"") | H8: =IFERROR(IF(YTO!H7="","",YTO!H7),"") | I8: =IFERROR(IF(YTO!I7="","",YTO!I7),"") -> 17400 | J8: =IFERROR(IF(YTO!J7="","",YTO!J7),"") -> 21200 | ... L8: =IFERROR(IF(YTO!L7="","",YTO!L7),"") -> 31144
B9: STO | C9: =IFERROR(IF(STO!C7="","",STO!C7),"") | D9: =IFERROR(IF(STO!D7="","",STO!D7),"") | E9: =IFERROR(IF(STO!E7="","",STO!E7),"") | F9: =IFERROR(IF(STO!F7="","",STO!F7),"") | G9: =IFERROR(IF(STO!G7="","",STO!G7),"") | H9: =IFERROR(IF(STO!H7="","",STO!H7),"") | I9: =IFERROR(IF(STO!I7="","",STO!I7),"") -> 12900 | J9: =IFERROR(IF(STO!J7="","",STO!J7),"") | ... L9: =IFERROR(IF(STO!L7="","",STO!L7),"") -> 26139
B10: Yunda | C10: =IFERROR(IF(Yunda!C7="","",Yunda!C7),"") | D10: =IFERROR(IF(Yunda!D7="","",Yunda!D7),"") | E10: =IFERROR(IF(Yunda!E7="","",Yunda!E7),"") | F10: =IFERROR(IF(Yunda!F7="","",Yunda!F7),"") | G10: =IFERROR(IF(Yunda!G7="","",Yunda!G7),"") | H10: =IFERROR(IF(Yunda!H7="","",Yunda!H7),"") | I10: =IFERROR(IF(Yunda!I7="","",Yunda!I7),"") -> 17600 | J10: =IFERROR(IF(Yunda!J7="","",Yunda!J7),"") -> 18854 | ... L10: =IFERROR(IF(Yunda!L7="","",Yunda!L7),"") -> 25601
B11: Unit revenue (RMB)
B12: ZTO — as reported (NETS OUT delivery fee) | C12: =IFERROR(IF(ZTO!C29="","",ZTO!C29),"") | D12: =IFERROR(IF(ZTO!D29="","",ZTO!D29),"") | E12: =IFERROR(IF(ZTO!E29="","",ZTO!E29),"") | F12: =IFERROR(IF(ZTO!F29="","",ZTO!F29),"") | G12: =IFERROR(IF(ZTO!G29="","",ZTO!G29),"") | H12: =IFERROR(IF(ZTO!H29="","",ZTO!H29),"") | I12: =IFERROR(IF(ZTO!I29="","",ZTO!I29),"") -> 1.34 | J12: =IFERROR(IF(ZTO!J29="","",ZTO!J29),"") -> 1.24 | ... L12: =IFERROR(IF(ZTO!L29="","",ZTO!L29),"") | M12: Not comparable with the three below
B13: ZTO — normalised (+RMB1.25) | C13: =IFERROR(IF(C12="","",C12+1.25),"") | D13: =IFERROR(IF(D12="","",D12+1.25),"") | E13: =IFERROR(IF(E12="","",E12+1.25),"") | F13: =IFERROR(IF(F12="","",F12+1.25),"") | G13: =IFERROR(IF(G12="","",G12+1.25),"") | H13: =IFERROR(IF(H12="","",H12+1.25),"") | I13: =IFERROR(IF(I12="","",I12+1.25),"") -> 2.59 | J13: =IFERROR(IF(J12="","",J12+1.25),"") -> 2.49 | ... L13: =IFERROR(IF(L12="","",L12+1.25),"") | M13: Reported plus the assumed delivery fee
B14: YTO | C14: =IFERROR(IF(YTO!C17="","",YTO!C17),"") | D14: =IFERROR(IF(YTO!D17="","",YTO!D17),"") | E14: =IFERROR(IF(YTO!E17="","",YTO!E17),"") | F14: =IFERROR(IF(YTO!F17="","",YTO!F17),"") | G14: =IFERROR(IF(YTO!G17="","",YTO!G17),"") | H14: =IFERROR(IF(YTO!H17="","",YTO!H17),"") | I14: =IFERROR(IF(YTO!I17="","",YTO!I17),"") -> 2.59 | J14: =IFERROR(IF(YTO!J17="","",YTO!J17),"") -> 2.41 | ... L14: =IFERROR(IF(YTO!L17="","",YTO!L17),"") -> 2.19
B15: STO | C15: =IFERROR(IF(STO!C14="","",STO!C14),"") | D15: =IFERROR(IF(STO!D14="","",STO!D14),"") | E15: =IFERROR(IF(STO!E14="","",STO!E14),"") | F15: =IFERROR(IF(STO!F14="","",STO!F14),"") | G15: =IFERROR(IF(STO!G14="","",STO!G14),"") | H15: =IFERROR(IF(STO!H14="","",STO!H14),"") | I15: =IFERROR(IF(STO!I14="","",STO!I14),"") -> 2.52 | J15: =IFERROR(IF(STO!J14="","",STO!J14),"") | ... L15: =IFERROR(IF(STO!L14="","",STO!L14),"") -> 2.1
B16: Yunda | C16: =IFERROR(IF(Yunda!C16="","",Yunda!C16),"") | D16: =IFERROR(IF(Yunda!D16="","",Yunda!D16),"") | E16: =IFERROR(IF(Yunda!E16="","",Yunda!E16),"") | F16: =IFERROR(IF(Yunda!F16="","",Yunda!F16),"") | G16: =IFERROR(IF(Yunda!G16="","",Yunda!G16),"") | H16: =IFERROR(IF(Yunda!H16="","",Yunda!H16),"") | I16: =IFERROR(IF(Yunda!I16="","",Yunda!I16),"") -> 2.55 | J16: =IFERROR(IF(Yunda!J16="","",Yunda!J16),"") | ... L16: =IFERROR(IF(Yunda!L16="","",Yunda!L16),"") -> 1.983
B17: Unit cost (RMB)
B18: ZTO — as reported | C18: =IFERROR(IF(ZTO!C30="","",ZTO!C30),"") | D18: =IFERROR(IF(ZTO!D30="","",ZTO!D30),"") | E18: =IFERROR(IF(ZTO!E30="","",ZTO!E30),"") | F18: =IFERROR(IF(ZTO!F30="","",ZTO!F30),"") | G18: =IFERROR(IF(ZTO!G30="","",ZTO!G30),"") | H18: =IFERROR(IF(ZTO!H30="","",ZTO!H30),"") | I18: =IFERROR(IF(ZTO!I30="","",ZTO!I30),"") | J18: =IFERROR(IF(ZTO!J30="","",ZTO!J30),"") -> 0.86 | ... L18: =IFERROR(IF(ZTO!L30="","",ZTO!L30),"") -> 0.94 | M18: Ex-delivery fee, ex-freight forwarding
B19: ZTO — normalised (+RMB1.25) | C19: =IFERROR(IF(C18="","",C18+1.25),"") | D19: =IFERROR(IF(D18="","",D18+1.25),"") | E19: =IFERROR(IF(E18="","",E18+1.25),"") | F19: =IFERROR(IF(F18="","",F18+1.25),"") | G19: =IFERROR(IF(G18="","",G18+1.25),"") | H19: =IFERROR(IF(H18="","",H18+1.25),"") | I19: =IFERROR(IF(I18="","",I18+1.25),"") | J19: =IFERROR(IF(J18="","",J18+1.25),"") -> 2.11 | ... L19: =IFERROR(IF(L18="","",L18+1.25),"") -> 2.19
B20: YTO | C20: =IFERROR(IF(YTO!C18="","",YTO!C18),"") | D20: =IFERROR(IF(YTO!D18="","",YTO!D18),"") | E20: =IFERROR(IF(YTO!E18="","",YTO!E18),"") | F20: =IFERROR(IF(YTO!F18="","",YTO!F18),"") | G20: =IFERROR(IF(YTO!G18="","",YTO!G18),"") | H20: =IFERROR(IF(YTO!H18="","",YTO!H18),"") | I20: =IFERROR(IF(YTO!I18="","",YTO!I18),"") | J20: =IFERROR(IF(YTO!J18="","",YTO!J18),"") -> 2.18 | ... L20: =IFERROR(IF(YTO!L18="","",YTO!L18),"") -> 2
B21: STO | C21: =IFERROR(IF(STO!C15="","",STO!C15),"") | D21: =IFERROR(IF(STO!D15="","",STO!D15),"") | E21: =IFERROR(IF(STO!E15="","",STO!E15),"") | F21: =IFERROR(IF(STO!F15="","",STO!F15),"") | G21: =IFERROR(IF(STO!G15="","",STO!G15),"") | H21: =IFERROR(IF(STO!H15="","",STO!H15),"") | I21: =IFERROR(IF(STO!I15="","",STO!I15),"") | J21: =IFERROR(IF(STO!J15="","",STO!J15),"") -> 2.15 | ... L21: =IFERROR(IF(STO!L15="","",STO!L15),"") -> 1.98
B22: Yunda | C22: =IFERROR(IF(Yunda!C17="","",Yunda!C17),"") | D22: =IFERROR(IF(Yunda!D17="","",Yunda!D17),"") | E22: =IFERROR(IF(Yunda!E17="","",Yunda!E17),"") | F22: =IFERROR(IF(Yunda!F17="","",Yunda!F17),"") | G22: =IFERROR(IF(Yunda!G17="","",Yunda!G17),"") | H22: =IFERROR(IF(Yunda!H17="","",Yunda!H17),"") | I22: =IFERROR(IF(Yunda!I17="","",Yunda!I17),"") -> 2.34 | J22: =IFERROR(IF(Yunda!J17="","",Yunda!J17),"") -> 2.1 | ... L22: =IFERROR(IF(Yunda!L17="","",Yunda!L17),"") -> 1.85
B23: Comparable legs — directly comparable across all four
B24: ZTO — line-haul | C24: =IFERROR(IF(ZTO!C31="","",ZTO!C31),"") | D24: =IFERROR(IF(ZTO!D31="","",ZTO!D31),"") | E24: =IFERROR(IF(ZTO!E31="","",ZTO!E31),"") | F24: =IFERROR(IF(ZTO!F31="","",ZTO!F31),"") | G24: =IFERROR(IF(ZTO!G31="","",ZTO!G31),"") | H24: =IFERROR(IF(ZTO!H31="","",ZTO!H31),"") | I24: =IFERROR(IF(ZTO!I31="","",ZTO!I31),"") | J24: =IFERROR(IF(ZTO!J31="","",ZTO!J31),"") | ... L24: =IFERROR(IF(ZTO!L31="","",ZTO!L31),"") -> 0.36
B25: YTO — transport | C25: =IFERROR(IF(YTO!C19="","",YTO!C19),"") | D25: =IFERROR(IF(YTO!D19="","",YTO!D19),"") | E25: =IFERROR(IF(YTO!E19="","",YTO!E19),"") | F25: =IFERROR(IF(YTO!F19="","",YTO!F19),"") | G25: =IFERROR(IF(YTO!G19="","",YTO!G19),"") | H25: =IFERROR(IF(YTO!H19="","",YTO!H19),"") | I25: =IFERROR(IF(YTO!I19="","",YTO!I19),"") | J25: =IFERROR(IF(YTO!J19="","",YTO!J19),"") | ... L25: =IFERROR(IF(YTO!L19="","",YTO!L19),"") -> 0.37
B26: STO — transport | C26: =IFERROR(IF(STO!C18="","",STO!C18),"") | D26: =IFERROR(IF(STO!D18="","",STO!D18),"") | E26: =IFERROR(IF(STO!E18="","",STO!E18),"") | F26: =IFERROR(IF(STO!F18="","",STO!F18),"") | G26: =IFERROR(IF(STO!G18="","",STO!G18),"") | H26: =IFERROR(IF(STO!H18="","",STO!H18),"") | I26: =IFERROR(IF(STO!I18="","",STO!I18),"") | J26: =IFERROR(IF(STO!J18="","",STO!J18),"") | ... L26: =IFERROR(IF(STO!L18="","",STO!L18),"") -> 0.39
B27: Yunda — transport | C27: =IFERROR(IF(Yunda!C19="","",Yunda!C19),"") | D27: =IFERROR(IF(Yunda!D19="","",Yunda!D19),"") | E27: =IFERROR(IF(Yunda!E19="","",Yunda!E19),"") | F27: =IFERROR(IF(Yunda!F19="","",Yunda!F19),"") | G27: =IFERROR(IF(Yunda!G19="","",Yunda!G19),"") | H27: =IFERROR(IF(Yunda!H19="","",Yunda!H19),"") | I27: =IFERROR(IF(Yunda!I19="","",Yunda!I19),"") | J27: =IFERROR(IF(Yunda!J19="","",Yunda!J19),"") -> 0.5 | ... L27: =IFERROR(IF(Yunda!L19="","",Yunda!L19),"")
B28: ZTO — sorting | C28: =IFERROR(IF(ZTO!C32="","",ZTO!C32),"") | D28: =IFERROR(IF(ZTO!D32="","",ZTO!D32),"") | E28: =IFERROR(IF(ZTO!E32="","",ZTO!E32),"") | F28: =IFERROR(IF(ZTO!F32="","",ZTO!F32),"") | G28: =IFERROR(IF(ZTO!G32="","",ZTO!G32),"") | H28: =IFERROR(IF(ZTO!H32="","",ZTO!H32),"") | I28: =IFERROR(IF(ZTO!I32="","",ZTO!I32),"") | J28: =IFERROR(IF(ZTO!J32="","",ZTO!J32),"") | ... L28: =IFERROR(IF(ZTO!L32="","",ZTO!L32),"") -> 0.26
B29: YTO — hub operating | C29: =IFERROR(IF(YTO!C20="","",YTO!C20),"") | D29: =IFERROR(IF(YTO!D20="","",YTO!D20),"") | E29: =IFERROR(IF(YTO!E20="","",YTO!E20),"") | F29: =IFERROR(IF(YTO!F20="","",YTO!F20),"") | G29: =IFERROR(IF(YTO!G20="","",YTO!G20),"") | H29: =IFERROR(IF(YTO!H20="","",YTO!H20),"") | I29: =IFERROR(IF(YTO!I20="","",YTO!I20),"") | J29: =IFERROR(IF(YTO!J20="","",YTO!J20),"") | ... L29: =IFERROR(IF(YTO!L20="","",YTO!L20),"") -> 0.27
B30: STO — sorting | C30: =IFERROR(IF(STO!C17="","",STO!C17),"") | D30: =IFERROR(IF(STO!D17="","",STO!D17),"") | E30: =IFERROR(IF(STO!E17="","",STO!E17),"") | F30: =IFERROR(IF(STO!F17="","",STO!F17),"") | G30: =IFERROR(IF(STO!G17="","",STO!G17),"") | H30: =IFERROR(IF(STO!H17="","",STO!H17),"") | I30: =IFERROR(IF(STO!I17="","",STO!I17),"") | J30: =IFERROR(IF(STO!J17="","",STO!J17),"") | ... L30: =IFERROR(IF(STO!L17="","",STO!L17),"") -> 0.31
B31: Yunda — sorting | C31: =IFERROR(IF(Yunda!C20="","",Yunda!C20),"") | D31: =IFERROR(IF(Yunda!D20="","",Yunda!D20),"") | E31: =IFERROR(IF(Yunda!E20="","",Yunda!E20),"") | F31: =IFERROR(IF(Yunda!F20="","",Yunda!F20),"") | G31: =IFERROR(IF(Yunda!G20="","",Yunda!G20),"") | H31: =IFERROR(IF(Yunda!H20="","",Yunda!H20),"") | I31: =IFERROR(IF(Yunda!I20="","",Yunda!I20),"") | J31: =IFERROR(IF(Yunda!J20="","",Yunda!J20),"") -> 0.37 | ... L31: =IFERROR(IF(Yunda!L20="","",Yunda!L20),"")
B33: Normalisation: ZTO nets the franchisee delivery fee out of both revenue and cost; the other three gross it up. The RMB1.25 add-back is anchored on STO's disclosed unit pickup-and-delivery cost of RMB1.27 (2025) and Yunda's disclosed unit delivery fee of RMB1.21 (2023).
B34: The transport and sorting rows at the bottom need NO adjustment — those legs are defined the same way by all four, and are the cleanest like-for-like efficiency comparison available.

Sheet Sources
B2: Sources & where to fill the gaps
B3: Primary filing repositories listed first for each company.
B5: Company | C5: Document | D5: Type | E5: Link
B6: — PRIMARY REPOSITORIES —
B7: ZTO | C7: SEC EDGAR filing index, CIK 1677250 — all annual 6-K exhibits and 20-Fs | D7: Primary | E7: https://www.sec.gov/cgi-bin/browse-edgar?action=getcompany&CIK=1677250&type=6-K
B8: ZTO | C8: Investor room — all quarterly and annual releases | D8: Primary | E8: https://zto.investorroom.com/
B9: YTO / STO / Yunda | C9: CNINFO — official PRC disclosure portal. Search ticker, filter 年度报告 | D9: Primary | E9: http://www.cninfo.com.cn/
B10: Yunda | C10: SZSE disclosure portal | D10: Primary | E10: https://www.szse.cn/disclosure/listed/notice/
B11: — ZTO, YEAR BY YEAR —
B12: ZTO | C12: FY2018 results 6-K Ex-99.1 — full FY2017 & FY2018 P&L, cost lines, cash flow | D12: Primary | E12: https://www.sec.gov/Archives/edgar/data/1677250/000110465919015351/a19-6586_1ex99d1.htm
B13: ZTO | C13: FY2019 results 6-K Ex-99.1 — 12.1bn parcels, OCF RMB6.3bn | D13: Primary | E13: https://www.sec.gov/Archives/edgar/data/1677250/000110465920035558/a20-13098_1ex99d1.htm
B14: ZTO | C14: FY2021 results — 22.3bn parcels, revenue RMB30,405.8mn, OCF RMB7,220.2mn | D14: Primary | E14: https://www.prnewswire.com/news-releases/zto-reports-fourth-quarter-2021-and-fiscal-year-2021-unaudited-financial-results-301504152.html
B15: ZTO | C15: FY2022 results — revenue RMB35,377.0mn, GP RMB9,039.3mn, adj NI RMB6,806.0mn | D15: Primary | E15: https://zto.investorroom.com/2023-03-15-ZTO-Reports-Fourth-Quarter-2022-and-Full-Year-2022-Unaudited-Financial-Results
B16: ZTO | C16: FY2023 results — 30.2bn parcels, adj NI RMB9.0bn, OCF RMB13,361.0mn | D16: Primary | E16: https://www.prnewswire.com/news-releases/zto-reports-fourth-quarter-2023-and-full-year-2023-unaudited-financial-results-302093211.html
B17: ZTO | C17: FY2024 results — adj NI RMB10.2bn, OCF RMB11,429.4mn | D17: Primary | E17: https://www.prnewswire.com/apac/news-releases/zto-reports-fourth-quarter-2024-and-full-year-2024-unaudited-financial-results-302404760.html
B18: ZTO | C18: FY2024 earnings call — capex RMB5.9bn, COGS RMB30.6bn, GP RMB13.7bn, GM 31.0% | D18: Transcript | E18: https://finance.yahoo.com/news/zto-express-cayman-inc-zto-070029100.html
B19: ZTO | C19: FY2025 results 6-K Ex-99.1 — full P&L and unit cost detail | D19: Primary | E19: https://www.sec.gov/Archives/edgar/data/1677250/000110465926030007/tm269230d1_ex99-1.htm
B20: — A-SHARE NAMES —
B21: YTO | C21: FY2025 annual report summary, CNINFO | D21: Primary | E21: http://dataclouds.cninfo.com.cn/shgonggao/hsomarket/2026/20260422/fa3d52a190e54e3aae4a020d7823ec47.PDF
B22: YTO | C22: FY2025 unit transport / hub cost detail | D22: Press | E22: https://stock.stockstar.com/IG2026042200052531.shtml
B23: YTO | C23: FY2024 — volume 26.573bn, express revenue RMB60.9bn, segment gross margins | D23: Press | E23: https://www.stcn.com/article/detail/1734116.html
B24: Yunda | C24: FY2025 annual report summary, SZSE | D24: Primary | E24: https://disc.static.szse.cn/disc/disk03/finalpage/2026-04-25/f6ea5552-0a7b-4f6c-a787-b4962bdf81ed.PDF
B25: Yunda | C25: FY2025 — revenue RMB51,475mn, net profit RMB1,171mn (-38.79%) | D25: Press | E25: https://finance.cnr.cn/ycbd/20260425/t20260425_527599983.shtml
B26: Yunda / YTO / STO | C26: FY2023 leg-level unit costs — Yunda 2.10 total (transport 0.50 / sorting 0.37 / delivery 1.21), YTO 2.18, STO 2.15 | D26: Analysis | E26: https://news.qq.com/rain/a/20240501A06UW400
B27: STO / ZTO / J&T | C27: FY2025 leg-level unit costs — STO 1.98 (1.27 / 0.31 / 0.39), ZTO 0.94, J&T China USD0.28 | D27: Analysis | E27: https://www.huxiu.com/article/4862999.html
B28: All four | C28: FY2024 volume and share table — ZTO 34.0bn, YTO 26.6bn, Yunda 23.8bn, STO 22.7bn | D28: Press | E28: https://www.nbd.com.cn/articles/2025-01-27/3738264.html
B29: All four | C29: FY2022 unit revenue table — SF 15.73, YTO 2.59, Yunda 2.55, STO 2.52, ZTO 1.34 | D29: Analysis | E29: https://zhuanlan.zhihu.com/p/641739686
B30: All four | C30: Cumulative 2016–2023 capex — ZTO RMB47.3bn vs YTO RMB30.6bn | D30: Broker | E30: https://reportify-1252068037.cos.ap-beijing.myqcloud.com/media/production/s_c7800a1b_c7800a1b89250ed2fe72d28dca36baf7.pdf
B31: Industry | C31: State Post Bureau FY2025 — 199.0bn parcels, revenue RMB1.5tn | D31: Primary | E31: https://www.chinanews.com.cn/cj/2026/01-22/10557017.shtml
